odoo/addons/product_lot_sequence/README.rst
odoo/addons/product_lot_sequence/__init__.py
odoo/addons/product_lot_sequence/__manifest__.py
odoo/addons/product_lot_sequence/data/ir_config_parameter.xml
odoo/addons/product_lot_sequence/i18n/ca.po
odoo/addons/product_lot_sequence/i18n/es.po
odoo/addons/product_lot_sequence/i18n/fr.po
odoo/addons/product_lot_sequence/i18n/it.po
odoo/addons/product_lot_sequence/i18n/nl.po
odoo/addons/product_lot_sequence/i18n/nl_NL.po
odoo/addons/product_lot_sequence/i18n/product_lot_sequence.pot
odoo/addons/product_lot_sequence/models/__init__.py
odoo/addons/product_lot_sequence/models/product.py
odoo/addons/product_lot_sequence/models/res_company.py
odoo/addons/product_lot_sequence/models/res_config_settings.py
odoo/addons/product_lot_sequence/models/stock_lot.py
odoo/addons/product_lot_sequence/models/stock_move.py
odoo/addons/product_lot_sequence/readme/CONFIGURE.md
odoo/addons/product_lot_sequence/readme/CONTRIBUTORS.md
odoo/addons/product_lot_sequence/readme/CREDITS.md
odoo/addons/product_lot_sequence/readme/DESCRIPTION.md
odoo/addons/product_lot_sequence/readme/ROADMAP.md
odoo/addons/product_lot_sequence/readme/USAGE.md
odoo/addons/product_lot_sequence/static/description/icon.png
odoo/addons/product_lot_sequence/static/description/index.html
odoo/addons/product_lot_sequence/tests/__init__.py
odoo/addons/product_lot_sequence/tests/test_product_lot_sequence.py
odoo/addons/product_lot_sequence/views/product_views.xml
odoo/addons/product_lot_sequence/views/res_config_settings_views.xml
odoo_addon_product_lot_sequence-18.0.1.0.0.2.dist-info/METADATA
odoo_addon_product_lot_sequence-18.0.1.0.0.2.dist-info/WHEEL
odoo_addon_product_lot_sequence-18.0.1.0.0.2.dist-info/top_level.txt
odoo_addon_product_lot_sequence-18.0.1.0.0.2.dist-info/RECORD
